cpcready/__init__.py
cpcready/cat/__init__.py
cpcready/cat/cat.py
cpcready/cli.py
cpcready/configweb/__init__.py
cpcready/configweb/configweb.py
cpcready/configweb/streamlit_app.py
cpcready/console/__init__.py
cpcready/console/console.py
cpcready/disc/__init__.py
cpcready/disc/disc.py
cpcready/drive/__init__.py
cpcready/drive/drive.py
cpcready/emu/__init__.py
cpcready/emu/emu.py
cpcready/era/__init__.py
cpcready/era/era.py
cpcready/filextr/__init__.py
cpcready/filextr/filextr.py
cpcready/list/__init__.py
cpcready/list/list.py
cpcready/m4/__init__.py
cpcready/m4/m4.py
cpcready/mode/__init__.py
cpcready/mode/mode.py
cpcready/model/__init__.py
cpcready/model/model.py
cpcready/pydsk/MIGRATION.md
cpcready/pydsk/README.md
cpcready/pydsk/__init__.py
cpcready/pydsk/basic_viewer.py
cpcready/pydsk/cli.py
cpcready/pydsk/demo_library.py
cpcready/pydsk/dsk.py
cpcready/pydsk/ejemplos/01_crear_dsk.py
cpcready/pydsk/ejemplos/02_listar_archivos.py
cpcready/pydsk/ejemplos/03_informacion_dsk.py
cpcready/pydsk/ejemplos/04_importar_archivos.py
cpcready/pydsk/ejemplos/05_exportar_archivos.py
cpcready/pydsk/ejemplos/06_renombrar_archivos.py
cpcready/pydsk/ejemplos/07_eliminar_archivos.py
cpcready/pydsk/ejemplos/08_visualizar_basic.py
cpcready/pydsk/ejemplos/09_detectar_tipo_archivo.py
cpcready/pydsk/ejemplos/10_cabecera_amsdos_externa.py
cpcready/pydsk/ejemplos/README.md
cpcready/pydsk/examples.py
cpcready/pydsk/exceptions.py
cpcready/pydsk/structures.py
cpcready/pydsk/test_cabeceras_amsdos.py
cpcready/pydsk/test_compatibility.py
cpcready/pydsk/test_errores_directos.py
cpcready/ren/__init__.py
cpcready/ren/ren.py
cpcready/run/__init__.py
cpcready/run/run.py
cpcready/rvm/__init__.py
cpcready/rvm/rvm.py
cpcready/save/__init__.py
cpcready/save/save.py
cpcready/schemas/config_schema.json
cpcready/schemas/default_config.yaml
cpcready/settings/__init__.py
cpcready/settings/settings.py
cpcready/user/__init__.py
cpcready/user/user.py
cpcready/utils/__init__.py
cpcready/utils/click_custom.py
cpcready-0.1.2.dist-info/METADATA
cpcready-0.1.2.dist-info/WHEEL
cpcready-0.1.2.dist-info/entry_points.txt
cpcready-0.1.2.dist-info/licenses/LICENSE.md
cpcready-0.1.2.dist-info/licenses/NOTICE.md
cpcready-0.1.2.dist-info/RECORD
