Metadata-Version: 2.4
Name: cpcready
Version: 0.1.2
Summary: CPCReady Toolchain
License: MIT
License-File: LICENSE.md
License-File: NOTICE.md
Author: destroyer
Author-email: destroyer.dcf@gmail.com
Requires-Python: >=3.10
Classifier: License :: OSI Approved :: MIT License
Classifier: Programming Language :: Python :: 3
Classifier: Programming Language :: Python :: 3.10
Classifier: Programming Language :: Python :: 3.11
Classifier: Programming Language :: Python :: 3.12
Classifier: Programming Language :: Python :: 3.13
Classifier: Programming Language :: Python :: 3.14
Requires-Dist: click (>=8.3.0,<9.0.0)
Requires-Dist: packaging (>=24.0,<25.0)
Requires-Dist: prompt-toolkit (>=3.0.52,<4.0.0)
Requires-Dist: psutil (>=7.1.0,<8.0.0)
Requires-Dist: questionary (>=2.1.1,<3.0.0)
Requires-Dist: requests (>=2.32.5,<3.0.0)
Requires-Dist: rich (>=14.2.0,<15.0.0)
Requires-Dist: tabulate (>=0.9.0,<0.10.0)
Requires-Dist: tomli (==1.1.0) ; python_version < "3.11"
Requires-Dist: tomli-w (>=1.1.0,<2.0.0)
